chrysalis/__init__.py
chrysalis/core.py
chrysalis/plots.py
chrysalis/utils.py
chrysalis/test/test.py
chrysalis_st-0.2.0.dist-info/METADATA
chrysalis_st-0.2.0.dist-info/WHEEL
chrysalis_st-0.2.0.dist-info/licenses/LICENSE
chrysalis_st-0.2.0.dist-info/RECORD
