Metadata-Version: 2.1
Name: chrysalis-st
Version: 0.2.0
Summary: Powerful and lightweight package to identify tissue compartments in spatial transcriptomics datasets.
Project-URL: Homepage, https://github.com/rockdeme/chrysalis
Project-URL: Documentation, https://chrysalis.readthedocs.io/
Author: Demeter Túrós
License-File: LICENSE
Classifier: License :: OSI Approved :: MIT License
Classifier: Operating System :: OS Independent
Classifier: Programming Language :: Python :: 3
Requires-Python: >=3.7
Requires-Dist: archetypes==0.4.2
Requires-Dist: matplotlib
Requires-Dist: numpy
Requires-Dist: pandas
Requires-Dist: pysal
Requires-Dist: scanpy
Requires-Dist: scikit-learn
Requires-Dist: scipy
Requires-Dist: seaborn
Requires-Dist: tqdm
